RotationLabelingTool/StartLabel.py
RotationLabelingTool/__init__.py
RotationLabelingTool/labelingTool/LabelingTool.py
RotationLabelingTool/labelingTool/__init__.py
RotationLabelingTool/tools/CvTool.py
RotationLabelingTool/tools/__init__.py
RotationLabelingTool/ui/__init__.py
RotationLabelingTool/ui/ui.py
RotationLabelingTool-1.0.0.dist-info/METADATA
RotationLabelingTool-1.0.0.dist-info/WHEEL
RotationLabelingTool-1.0.0.dist-info/top_level.txt
RotationLabelingTool-1.0.0.dist-info/RECORD
